lsap/__init__.py
lsap/capability/__init__.py
lsap/capability/abc.py
lsap/capability/definition.py
lsap/capability/locate.py
lsap/capability/outline.py
lsap/capability/reference.py
lsap/capability/rename.py
lsap/capability/search.py
lsap/capability/symbol.py
lsap/exception.py
lsap/schema/__init__.py
lsap/schema/__main__.py
lsap/schema/_abc.py
lsap/schema/definition.py
lsap/schema/draft/__init__.py
lsap/schema/draft/completion.py
lsap/schema/draft/diagnostics.py
lsap/schema/draft/hierarchy.py
lsap/schema/draft/inlay_hint.py
lsap/schema/draft/relation.py
lsap/schema/draft/test_relation.py
lsap/schema/locate.py
lsap/schema/models.py
lsap/schema/outline.py
lsap/schema/reference.py
lsap/schema/rename.py
lsap/schema/search.py
lsap/schema/symbol.py
lsap/schema/types.py
lsap/utils/__init__.py
lsap/utils/cache.py
lsap/utils/capability.py
lsap/utils/document.py
lsap/utils/id.py
lsap/utils/locate.py
lsap/utils/markdown.py
lsap/utils/pagination.py
lsap/utils/symbol.py
lsap_sdk-0.2.0.dist-info/WHEEL
lsap_sdk-0.2.0.dist-info/METADATA
lsap_sdk-0.2.0.dist-info/RECORD
