Metadata-Version: 2.3
Name: lsap-sdk
Version: 0.2.0
Summary: Language Server Agent Protocol (LSAP) SDK - Transforms low-level LSP into high-level cognitive tools for agents
Keywords: Language Server Protocol,LSP,LSAP,Agent,AI SDK
Author: observerw
Author-email: observerw <wozluohd@gmail.com>
Classifier: Programming Language :: Python
Classifier: Programming Language :: Python :: 3.12
Classifier: License :: OSI Approved :: MIT License
Requires-Dist: anyio>=4.12.0
Requires-Dist: asyncer>=0.0.11
Requires-Dist: attrs>=25.4.0
Requires-Dist: cattrs>=25.3.0
Requires-Dist: loguru>=0.7.3
Requires-Dist: lsp-client>=0.3.6
Requires-Dist: lsprotocol>=2025.0.0
Requires-Dist: pydantic>=2.12.5
Requires-Dist: python-liquid>=2.1.0
Requires-Python: >=3.12
